nnoir_chainer/__init__.py
nnoir_chainer/_version.py
nnoir_chainer/configuration.py
nnoir_chainer/graph.py
nnoir_chainer/nnoir_function.py
nnoir_chainer/patch.py
nnoir_chainer/converter/__init__.py
nnoir_chainer/converter/add.py
nnoir_chainer/converter/add_constant.py
nnoir_chainer/converter/average_pooling_2d.py
nnoir_chainer/converter/batch_normalization.py
nnoir_chainer/converter/bias.py
nnoir_chainer/converter/bilinear_2d.py
nnoir_chainer/converter/broadcast.py
nnoir_chainer/converter/clipped_relu.py
nnoir_chainer/converter/concat.py
nnoir_chainer/converter/convolution_2d.py
nnoir_chainer/converter/depthwise_convolution_2d.py
nnoir_chainer/converter/dropout.py
nnoir_chainer/converter/elu.py
nnoir_chainer/converter/leaky_relu.py
nnoir_chainer/converter/linear.py
nnoir_chainer/converter/local_response_normalization.py
nnoir_chainer/converter/max_pooling_2d.py
nnoir_chainer/converter/mul.py
nnoir_chainer/converter/mul_constant.py
nnoir_chainer/converter/pad.py
nnoir_chainer/converter/relu.py
nnoir_chainer/converter/reshape.py
nnoir_chainer/converter/scale.py
nnoir_chainer/converter/sigmoid.py
nnoir_chainer/converter/softmax.py
nnoir_chainer/converter/softmax_cross_entropy.py
nnoir_chainer/converter/sub.py
nnoir_chainer/converter/sum.py
nnoir_chainer/converter/swish.py
nnoir_chainer/converter/tanh.py
nnoir_chainer/converter/transpose.py
nnoir_chainer/converter/unpooling_2d.py
nnoir_chainer/functions/__init__.py
nnoir_chainer/functions/activation/__init__.py
nnoir_chainer/functions/activation/clipped_relu.py
nnoir_chainer/functions/activation/elu.py
nnoir_chainer/functions/activation/leaky_relu.py
nnoir_chainer/functions/activation/relu.py
nnoir_chainer/functions/activation/sigmoid.py
nnoir_chainer/functions/activation/softmax.py
nnoir_chainer/functions/activation/tanh.py
nnoir_chainer/functions/array/__init__.py
nnoir_chainer/functions/array/broadcast.py
nnoir_chainer/functions/array/concat.py
nnoir_chainer/functions/array/pad.py
nnoir_chainer-1.1.3.dist-info/METADATA
nnoir_chainer-1.1.3.dist-info/WHEEL
nnoir_chainer-1.1.3.dist-info/top_level.txt
nnoir_chainer-1.1.3.dist-info/RECORD
