Metadata-Version: 2.1
Name: nnoir-chainer
Version: 1.1.3
Summary: Chainer from/to NNOIR Converter
Home-page: https://github.com/Idein/nnoir/tree/master/nnoir-chainer
Author: Idein Inc.
Author-email: n.ohkawa@idein.jp
License: MIT
Keywords: nnoir machine learning chainer
Platform: UNKNOWN
Classifier: Development Status :: 4 - Beta
Classifier: Intended Audience :: Developers
Classifier: License :: OSI Approved :: MIT License
Classifier: Programming Language :: Python :: 3 :: Only
Requires-Dist: chainer
Requires-Dist: numpy
Requires-Dist: msgpack
Requires-Dist: nnoir
